{
  "meta": {
    "filler": "未填写",
    "week": "W24 (6/8-6/14)",
    "exportTime": "2026-06-11T00:13:37.305Z"
  },
  "task_closed": [],
  "org_dynamic": [],
  "biz_dynamic": [
    {
      "category": "已有项目评审",
      "rows": [
        [
          "主轴拧紧",
          "二次FAT",
          "20%",
          "6/10已完成安装通电",
          "软件开发进度Delay",
          "低",
          "80%",
          "昌文盛"
        ],
        [
          "沧州充放电半自动设备",
          "硬件设计",
          "0%",
          "",
          "商务洽谈中，机械方案已冻结，已报备PDT前置电气硬件设计工作(5天)",
          "低",
          "20%",
          "昌文盛"
        ],
        [
          "沧州圆柱",
          "SAT",
          "",
          "6/1已启动FAT，一/二次注液机8个关闭项，其余机台暂未收到关闭项清单",
          "一次注液机 突发安全I/O模块通讯超时 2次/天",
          "中",
          "100%",
          "梁志强"
        ],
        [
          "江阴圆柱钢壳清洗机新增静电除尘功能",
          "验收&培训&交付",
          "100",
          "已完成",
          "无",
          "低",
          "70%",
          "杨振雄"
        ],
        [
          "沧州二期倒立除尘",
          "部装阶段/程序优化",
          "60",
          "增加MES、除尘数据读取传递",
          "无",
          "低",
          "30%",
          "杨振雄"
        ],
        [
          "法国-缓存线",
          "部装阶段/CE资料第二轮评审",
          "90%",
          "7/8—已完成95%第二轮评审预计本周完成，1/8—设备手册编写10%",
          "无",
          "低",
          "90%",
          "陈彩虹"
        ],
        [
          "UK",
          "与动力重新规划机台责任",
          "50%",
          "原则已拉通一致，预计周5输出初版划分",
          "无",
          "低",
          "50%",
          "梁志强"
        ],
        [
          "IK",
          "与动力责任划分MES数据已划分清楚",
          "100",
          "",
          "无",
          "低",
          "",
          "李钦"
        ]
      ]
    }
  ],
  "compliance": [
    [
      "点击下方按钮添加事项"
    ]
  ],
  "decision": [],
  "other": [
    [
      "盘点26年下半年人力",
      "应对业务新增需求",
      "按照当前实际任务，更新共享表格数据",
      "梁志强"
    ]
  ]
}